README.md
setup.cfg
setup.py
ton_client/__init__.py
ton_client/client.py
ton_client/tonlib.py
ton_client/utils.py
ton_client.egg-info/PKG-INFO
ton_client.egg-info/SOURCES.txt
ton_client.egg-info/dependency_links.txt
ton_client.egg-info/requires.txt
ton_client.egg-info/top_level.txt
ton_client.egg-info/zip-safe
ton_client/distlib/darwin/libtonlibjson.dylib
ton_client/distlib/linux/libtonlibjson.so