Metadata-Version: 1.2
Name: ton-client
Version: 0.5.1
Summary: ton client
Home-page: UNKNOWN
Author: Oleg Gaidukov
License: UNKNOWN
Keywords: ton gram
Platform: UNKNOWN
Requires-Python: >=3.7
